UI_files/SAM2Long.ui
model/.gitkeep
napari_sam2long/__init__.py
napari_sam2long/_version.py
napari_sam2long/_widget.py
napari_sam2long/napari.yaml
napari_sam2long/_tests/__init__.py
napari_sam2long/_tests/test_widget.py
napari_sam2long-1.0.3.dist-info/licenses/LICENSE
napari_sam2long-1.0.3.dist-info/licenses/NOTICE
pipelines/sam2long/SAM2Long_pipeline_handler.py
napari_sam2long-1.0.3.dist-info/METADATA
napari_sam2long-1.0.3.dist-info/WHEEL
napari_sam2long-1.0.3.dist-info/entry_points.txt
napari_sam2long-1.0.3.dist-info/top_level.txt
napari_sam2long-1.0.3.dist-info/RECORD
