Metadata-Version: 2.4
Name: napari-sam2long
Version: 1.0.3
Summary: A plugin for interactive 3D (volumetric or time-lapse) segmentation using Meta's Segment Anything Model 2 (SAM2).
Author: Mai Hoang
Author-email: maihan.hoang1208@gmail.com
License: 
Project-URL: Homepage, https://github.com/maihanhoang/napari-sam2long
Project-URL: Bug Tracker, https://github.com/maihanhoang/napari-sam2long/issues
Project-URL: Documentation, https://github.com/maihanhoang/napari-sam2long#README.md
Project-URL: Source Code, https://github.com/maihanhoang/napari-sam2long
Project-URL: User Support, https://github.com/maihanhoang/napari-sam2long/issues
Classifier: Development Status :: 2 - Pre-Alpha
Classifier: Framework :: napari
Classifier: Intended Audience :: Developers
Classifier: License :: Other/Proprietary License
Classifier: Operating System :: OS Independent
Classifier: Programming Language :: Python
Classifier: Programming Language :: Python :: 3
Classifier: Programming Language :: Python :: 3 :: Only
Classifier: Programming Language :: Python :: 3.10
Classifier: Programming Language :: Python :: 3.11
Classifier: Programming Language :: Python :: 3.12
Classifier: Programming Language :: Python :: 3.13
Classifier: Topic :: Scientific/Engineering :: Image Processing
Requires-Python: >=3.10
License-File: LICENSE
License-File: NOTICE
Requires-Dist: numpy
Requires-Dist: magicgui
Requires-Dist: qtpy
Requires-Dist: scikit-image
Requires-Dist: opencv-python
Requires-Dist: pytest
Provides-Extra: testing
Requires-Dist: tox; extra == "testing"
Requires-Dist: pytest; extra == "testing"
Requires-Dist: pytest-cov; extra == "testing"
Requires-Dist: pytest-qt; extra == "testing"
Requires-Dist: napari; extra == "testing"
Requires-Dist: pyqt5; extra == "testing"
Dynamic: license-file
